odoo/addons/sale_coupon_multi_gift/README.rst
odoo/addons/sale_coupon_multi_gift/__init__.py
odoo/addons/sale_coupon_multi_gift/__manifest__.py
odoo/addons/sale_coupon_multi_gift/i18n/es.po
odoo/addons/sale_coupon_multi_gift/i18n/sale_coupon_multi_gift.pot
odoo/addons/sale_coupon_multi_gift/models/__init__.py
odoo/addons/sale_coupon_multi_gift/models/coupon_program.py
odoo/addons/sale_coupon_multi_gift/models/sale_order.py
odoo/addons/sale_coupon_multi_gift/readme/CONFIGURE.rst
odoo/addons/sale_coupon_multi_gift/readme/CONTRIBUTORS.rst
odoo/addons/sale_coupon_multi_gift/readme/DESCRIPTION.rst
odoo/addons/sale_coupon_multi_gift/readme/ROADMAP.rst
odoo/addons/sale_coupon_multi_gift/readme/USAGE.rst
odoo/addons/sale_coupon_multi_gift/security/ir.model.access.csv
odoo/addons/sale_coupon_multi_gift/static/description/icon.png
odoo/addons/sale_coupon_multi_gift/static/description/index.html
odoo/addons/sale_coupon_multi_gift/tests/__init__.py
odoo/addons/sale_coupon_multi_gift/tests/test_sale_coupon_multi_gift.py
odoo_addon_sale_coupon_multi_gift-15.0.1.0.0.5.dist-info/METADATA
odoo_addon_sale_coupon_multi_gift-15.0.1.0.0.5.dist-info/WHEEL
odoo_addon_sale_coupon_multi_gift-15.0.1.0.0.5.dist-info/top_level.txt
odoo_addon_sale_coupon_multi_gift-15.0.1.0.0.5.dist-info/RECORD
